LICENSE
README.md
lyycalendar.py
setup.py
lyycalendar.egg-info/PKG-INFO
lyycalendar.egg-info/SOURCES.txt
lyycalendar.egg-info/dependency_links.txt
lyycalendar.egg-info/requires.txt
lyycalendar.egg-info/top_level.txt