Metadata-Version: 2.1
Name: lyycalendar
Version: 2.19
Summary: calendar for  lyy
Author: lyy
Author-email: 
License: MIT
License-File: LICENSE
Requires-Dist: pandas
